MANIFEST.in
README.rst
setup.py
articles_addons/__init__.py
articles_addons/admin.py
articles_addons/forms.py
articles_addons/models.py
articles_addons/urls.py
articles_addons/views.py
articles_addons/templatetags/__init__.py
articles_addons/templatetags/articles_extra_tags.py
django_articles_addons.egg-info/PKG-INFO
django_articles_addons.egg-info/SOURCES.txt
django_articles_addons.egg-info/dependency_links.txt
django_articles_addons.egg-info/requires.txt
django_articles_addons.egg-info/top_level.txt
django_articles_addons.egg-info/zip-safe