Metadata-Version: 1.0
Name: django-articles-addons
Version: 0.2.3
Summary: A collection of tools to extend codekoala's wonderful django-articless
Home-page: http://github.com/powellc/django-articles-addons
Author: Colin Powell
Author-email: colin@onecardinal.com
License: GPLv3
Download-URL: http://github.com/powellc/django-articles-addons/downloads
Platform: UNKNOWN
Classifier: Development Status :: 4 - Beta
Classifier: Environment :: Web Environment
Classifier: Intended Audience :: Developers
Classifier: License :: OSI Approved :: BSD License
Classifier: Operating System :: OS Independent
Classifier: Programming Language :: Python
Classifier: Framework :: Django
